Metadata-Version: 1.1
Name: note
Version: 0.5.2
Summary: A command line based note taking application
Home-page: https://github.com/dwwkelly/note
Author: Devin Kelly
Author-email: dwwkelly@fastmail.fm
License: GPL3
Keywords: note
Platform: UNKNOWN
Classifier: Development Status :: 2 - Pre-Alpha
Classifier: Intended Audience :: Developers
Classifier: License :: OSI Approved :: GNU General Public License v3 (GPLv3)
Classifier: Natural Language :: English
Classifier: Programming Language :: Python :: 2
Classifier: Programming Language :: Python :: 2.6
Classifier: Programming Language :: Python :: 2.7
